ip_model/Exceptions.py
ip_model/Ip.py
ip_model/IpObject.py
ip_model/Ipv4.py
ip_model/Ipv6.py
ip_model/Sample.py
ip_model/__init__.py
ip_model/util/Common.py
ip_model/util/IpTree.py
ip_model/util/Ipv4Tree.py
ip_model/util/Ipv6Tree.py
ip_model/util/RadixTree.py
ip_model/util/Validator.py
ip_model/util/__init__.py
ip_model_copy/Exceptions.py
ip_model_copy/Ipv4.py
ip_model_copy/Ipv6.py
ip_model_copy/__init__.py
ip_model_copy/util/Ipv4Tree.py
ip_model_copy/util/Ipv6Tree.py
ip_model_copy/util/Validator.py
ip_model_copy/util/__init__.py
tests/Exceptions.py
tests/__init__.py
tests/test_exceptions_ipv4.py
tests/test_exceptions_ipv6.py
tests/test_ip.py
tests/test_ipv4.py
tests/test_ipv6.py
util/RadixTree.py
util/Validator.py
util/__init__.py
ip_model-3.0.0.dist-info/LICENSE
ip_model-3.0.0.dist-info/METADATA
ip_model-3.0.0.dist-info/WHEEL
ip_model-3.0.0.dist-info/top_level.txt
ip_model-3.0.0.dist-info/RECORD
