Metadata-Version: 2.1
Name: ip-model
Version: 3.0.0
Summary: A Python package for storing, removing and checking IP's efficiently, Use cases: Blacklisting, Whitelisting etc
Home-page: https://github.com/rakesht2499/ip_model
Author: Rakesh Kumar T
Author-email: rakesht2499@gmail.com
License: Apache-2.0
Platform: UNKNOWN
Classifier: License :: OSI Approved :: Apache Software License
Classifier: Programming Language :: Python :: 3
Classifier: Programming Language :: Python :: 3.7
Classifier: Operating System :: OS Independent
Classifier: Topic :: Utilities
Classifier: Topic :: Software Development :: Libraries :: Python Modules
Classifier: Topic :: Software Development :: Libraries
